easymqtt.py
setup.cfg
setup.py
easymqtt.egg-info/PKG-INFO
easymqtt.egg-info/SOURCES.txt
easymqtt.egg-info/dependency_links.txt
easymqtt.egg-info/requires.txt
easymqtt.egg-info/top_level.txt