Metadata-Version: 1.1
Name: easymqtt
Version: 0.1.0
Summary: Ridiculously simple MQTT wrapper library
Home-page: https://gitlab.com/robconnolly/easymqtt
Author: Rob Connolly
Author-email: rob@webworxshop.com
License: MIT
Download-URL: https://gitlab.com/robconnolly/easymqtt/repository/archive.zip?ref=v0.1.0
Keywords: mqtt
Platform: UNKNOWN
